helloworks/__init__.py
helloworks/hwclient.py
helloworks/utils/__init__.py
helloworks/utils/access.py
helloworks/utils/api_endpoints.py
helloworks/utils/exceptions.py
helloworks/utils/helper.py
helloworks/utils/request.py
helloworks_python_sdk-0.4.dist-info/LICENSE
helloworks_python_sdk-0.4.dist-info/METADATA
helloworks_python_sdk-0.4.dist-info/WHEEL
helloworks_python_sdk-0.4.dist-info/top_level.txt
helloworks_python_sdk-0.4.dist-info/RECORD
