Metadata-Version: 2.1
Name: helloworks-python-sdk
Version: 0.4
Summary: A Python wrapper for the HelloWorks API  (https://portal.helloworks.com/)
Home-page: https://github.com/kevteg/helloworks-python-sdk
Author: kevteg
Author-email: kevteg05@gmail.com
License: MIT
Keywords: Helloworks python api sdk
Platform: UNKNOWN
Classifier: License :: OSI Approved :: MIT License
Classifier: Programming Language :: Python :: 3.4
Classifier: Programming Language :: Python :: 3.5
Classifier: Programming Language :: Python :: 3.6
Classifier: Programming Language :: Python :: 3.7
Classifier: Programming Language :: Python :: 3.8
Requires-Dist: requests
